monomer/__init__.py
monomer/__version__.py
monomer/column.py
monomer/compat.py
monomer/typemap.py
monomer/util.py
monomer-0.0.5.dist-info/LICENSE
monomer-0.0.5.dist-info/METADATA
monomer-0.0.5.dist-info/WHEEL
monomer-0.0.5.dist-info/top_level.txt
monomer-0.0.5.dist-info/RECORD
